genet/README.md
genet/__init__.py
genet/_dev/DeepPrimeBatch.py
genet/_dev/PredUtils.py
genet/_dev/UMI.py
genet/_dev/__init__.py
genet/_dev/dev_database.py
genet/_dev/dev_scripts.py
genet/_dev/download.py
genet/_dev/functional_dev.py
genet/analysis/Alignment.py
genet/analysis/GenBank.py
genet/analysis/OFFinder.py
genet/analysis/SGE_analysis.py
genet/analysis/SynPrime.py
genet/analysis/UMItools.py
genet/analysis/UMIutils.py
genet/analysis/__init__.py
genet/analysis/_dev_UMI.py
genet/analysis/constants.py
genet/analysis/functional.py
genet/analysis/mageck.py
genet/database/__init__.py
genet/database/config.py
genet/database/entrez.py
genet/database/functional.py
genet/design/DesignUtils.py
genet/design/TwinPE.py
genet/design/__init__.py
genet/design/functional.py
genet/design/ref_transcripts.py
genet/design/modules/__init__.py
genet/models/__init__.py
genet/models/constants.py
genet/models/functional.py
genet/predict/BaseEditor.py
genet/predict/DeepCas9Variants.py
genet/predict/DeepSmallCas9.py
genet/predict/Nuclease.py
genet/predict/PredUtils.py
genet/predict/PrimeEditor.py
genet/predict/__init__.py
genet/predict/functional.py
genet/utils/__init__.py
genet/utils/functional.py
genet-0.17.1.dist-info/METADATA
genet-0.17.1.dist-info/WHEEL
genet-0.17.1.dist-info/RECORD
