Metadata-Version: 2.3
Name: genet
Version: 0.17.1
Summary: GenET: Genome Editing Toolkit
Project-URL: Homepage, https://github.com/Goosang-Yu/genet
Project-URL: Repository, https://github.com/Goosang-Yu/genet
Project-URL: Source, https://github.com/Goosang-Yu/genet
Project-URL: Tracker, https://github.com/Goosang-Yu/genet/issues
Author-email: Goosang Yu <gsyu93@gmail.com>
License-Expression: MIT
Keywords: CRISPR,ai,analysis,bioinformatics,deep-learning,genetics,genome-editing,python
Classifier: Intended Audience :: Developers
Classifier: Intended Audience :: Science/Research
Classifier: License :: OSI Approved :: MIT License
Classifier: Operating System :: MacOS :: MacOS X
Classifier: Operating System :: POSIX
Classifier: Operating System :: Unix
Classifier: Programming Language :: Python
Classifier: Programming Language :: Python :: 3 :: Only
Classifier: Programming Language :: Python :: 3.9
Classifier: Programming Language :: Python :: 3.10
Classifier: Topic :: Software Development
Classifier: Topic :: Software Development :: Libraries
Classifier: Topic :: Software Development :: Libraries :: Application Frameworks
Classifier: Topic :: Software Development :: Libraries :: Python Modules
Requires-Python: >=3.9
Requires-Dist: biopython
Requires-Dist: editdistance
Requires-Dist: fastparquet
Requires-Dist: numpy<=1.26.4
Requires-Dist: pandas
Requires-Dist: protobuf<=3.20.3
Requires-Dist: pyarrow
Requires-Dist: regex
Requires-Dist: silence-tensorflow
Requires-Dist: tensorflow-macos<2.10.0; platform_system == 'Darwin'
Requires-Dist: tensorflow<2.10.0; platform_system != 'Darwin'
Requires-Dist: torch
Requires-Dist: tqdm
Requires-Dist: viennarna
